{
  "cardAsService": {
    "hero": {
      "bckgroundImage": "USPS/5.jpg",
      "heading": " Your brand. Your logic. Our infrastructure.",
      "descrip": "Get full control with SimpliFi’s Cards as a Service solution. Whether you're a fintech building a new product or an enterprise launching custom spend tools, our infrastructure powers every layer so you can create exactly what you need. From onboarding flows to KYC, from tokenization to fraud management, we’ve got the backend covered. You own the experience."
    },
    "clientMarquee": {
      "heading": "Trusted by fintechs, startups, and enterprises across MENA",
      "clientLogos": [
        { "name": "Floward", "logo": "/Logosweb/1.png" },
        { "name": "Walaplus", "logo": "/Logosweb/2.png" },
        { "name": "NQOODLET", "logo": "/Logosweb/3.png" },
        { "name": "Kamel Pay", "logo": "/Logosweb/4.png" },
        { "name": "Transportr", "logo": "/Logosweb/5.png" },
        { "name": "jisr", "logo": "/Logosweb/Jisr.png" }
      ]
    },
    "careerList": {
      "heading": "Future-proofing your card program",
      "descrip": "",
      "careerPositions": [
        {
          "title": "Modular by design",
          "href": "/careers/communication-designer",
          "location": "Prague or remote",
          "descrip": "Pick the layers you need and skip what you don’t. Build faster without compromising on your vision.",
          "icon":"icons/check.png"
        },
        {
          "title": "Made to scale",
          "href": "/careers/senior-designer-product",
          "location": "Prague or remote",
          "descrip": "Handle millions of transactions, complex approval flows, and real-time controls without friction.",
          "icon":"icons/check.png"
        },
        {
          "title": "Fully white-label",
          "href": "/careers/design-lead-product",
          "location": "Prague or remote",
          "descrip": "Your branding. Your workflows. We stay invisible so your brand stays front and center.",
          "icon":"icons/check.png"
        },
        {
          "title": "Built for compliance",
          "href": "/careers/creative-director-product",
          "location": "Prague or remote",
          "descrip": "We handle KYC, AML, 3DS, PCI-DSS, and more so you can focus on your product.",
          "icon":"icons/check.png"
        }
      ]
    },
    "useCases": {
      "title": "Our stack",
      "descrip": " Choose the layers you need. We’ll handle the rest.",

      "features": [
        {
          "id": 1,
          "company": "ING",
          "logo": "https://cdn.prod.website-files.com/660582dbf65d24242da5782d/6634e275076f072678348406_ing-userpic.webp",
          "title": "Frontend",
          "description": "Build your own cardholder and admin interfaces using our APIs. Enable real-time controls, card management, and custom workflows within your platform.",
          "image": "Cards-As-a-Service/Frontendlayer.jpg",
          "dark": false
        },
        {
          "id": 2,
          "company": "Société Générale Group",
          "logo": "https://cdn.prod.website-files.com/660582dbf65d24242da5782d/6634e2c46c7f5de93e2b0176_sgg-userpic.svg",
          "title": "Backend",
          "description": "Powerful APIs and webhooks for issuing, managing, and tracking cards. Easy integration with your systems.",
          "image": "Cards-As-a-Service/Backendlayer.jpg",
          "dark": true
        },
        {
          "id": 3,
          "company": "Moka",
          "logo": "https://cdn.prod.website-files.com/660582dbf65d24242da5782d/6634d315afb58424918a0b62_moka-userpick.svg",
          "title": "Regulatory",
          "description": "KYC, AML, and ongoing compliance covered. Stay compliant from day one.",
          "image": "Cards-As-a-Service/Regulatorylayer.jpg",
          "dark": false
        },
        {
          "id": 4,
          "company": "Oxygen",
          "logo": "https://cdn.prod.website-files.com/660582dbf65d24242da5782d/6634d35d4c5d6a3a3dd9bff9_oxygen-userpic.svg",
          "title": " Card Operations",
          "description": "We handle BIN sponsorship, funds management, and settlement. You focus on the experience.",
          "image": "Cards-As-a-Service/Bankinglayer.jpg",
          "dark": true,
          "horizontal": true
        },
        {
          "id": 5,
          "company": "Oxygen",
          "logo": "https://cdn.prod.website-files.com/660582dbf65d24242da5782d/6634d35d4c5d6a3a3dd9bff9_oxygen-userpic.svg",
          "title": "Support",
          "description": "Guidance from onboarding to launch. We assist with setup, integration, and daily operations.",
          "image": "Embed-Ready-To-Use-Card/Built-inSecurity andcompliance.jpg",
          "dark": true,
          "horizontal": true
        }
      ]
    },
    "whatsCookin": {
      "title": "Who we power",
      "subtitle": "",
      "slides": [
        {
          "src": "Cards-As-a-Service/Who it’s for Fintech launching product (2).jpg",
          "alt": "Landscape",
          "subtitle": "New research",
          "title": "Fintechs launching card products"
        },
        {
          "src": "Cards-As-a-Service/Who it’s for Enterprise building (2).jpg",
          "alt": "Landscape",
          "subtitle": "New research",
          "title": "Enterprises building internal spend tools"
        },
        {
          "src": "Cards-As-a-Service/Who it’s for Startups and scluping (2).jpg",
          "alt": "Landscape",
          "subtitle": "New research",
          "title": "Startups and scaleups building custom payment experiences"
        },
        {
          "src": "Cards-As-a-Service/Who it’s for Tech first term_ (2).jpg",
          "alt": "Landscape",
          "subtitle": "New research",
          "title": "Tech-first teams that need full control"
        }
      ]
    },
       "footer":{
      "bg-dark":true,
      "heading":"Ready to build your own card program?",
      "subheading":"We’ll provide the infrastructure, APIs, and compliance support. You build what matters.",
      "buttonText":"Book a Demo",
      "buttonLink":"/contact-us"
    }
  }
}
